{
  "unversionedId": "Tasks/plsql_basica",
  "id": "Tasks/plsql_basica",
  "title": "PRIMER BOLETÍN PL/SQL",
  "description": "PL/SQL",
  "source": "@site/docs/Tasks/plsql_basica.md",
  "sourceDirName": "Tasks",
  "slug": "/Tasks/plsql_basica",
  "permalink": "/docs/Tasks/plsql_basica",
  "draft": false,
  "editUrl": "https://github.com/belennazareth/ottershell/blob/main/docs/Tasks/plsql_basica.md",
  "tags": [],
  "version": "current",
  "sidebarPosition": 15,
  "frontMatter": {
    "sidebar_position": 15
  },
  "sidebar": "tutorialSidebar",
  "previous": {
    "title": "Migración CentOS",
    "permalink": "/docs/Tasks/migracion_centos"
  },
  "next": {
    "title": "Desarrollo y despliegue de una aplicación Java simple",
    "permalink": "/docs/Tasks/tomcat"
  }
}