{
  "/blog-94e": {
    "__comp": "a6aa9e1f",
    "__context": {
      "plugin": "777c682f"
    },
    "sidebar": "814f3328",
    "items": [
      {
        "content": "7661071f"
      }
    ],
    "metadata": "b2b675dd"
  },
  "/blog/archive-fd1": {
    "__comp": "9e4087bc",
    "__context": {
      "plugin": "777c682f"
    },
    "archive": "b2f554cd"
  },
  "/blog/Contacto-802": {
    "__comp": "ccc49370",
    "__context": {
      "plugin": "777c682f"
    },
    "sidebar": "814f3328",
    "content": "d9f32620"
  },
  "/blog/tags-098": {
    "__comp": "01a85c17",
    "__context": {
      "plugin": "777c682f"
    },
    "sidebar": "814f3328",
    "tags": "a7023ddc"
  },
  "/blog/tags/contacto-ecb": {
    "__comp": "6875c492",
    "__context": {
      "plugin": "777c682f"
    },
    "sidebar": "814f3328",
    "items": [
      {
        "content": "7661071f"
      }
    ],
    "tag": "2e872b27",
    "listMetadata": "1a6360f0"
  },
  "/blog/tags/git-hub-864": {
    "__comp": "6875c492",
    "__context": {
      "plugin": "777c682f"
    },
    "sidebar": "814f3328",
    "items": [
      {
        "content": "7661071f"
      }
    ],
    "tag": "ff917fbd",
    "listMetadata": "2455c74e"
  },
  "/blog/tags/gmail-d5b": {
    "__comp": "6875c492",
    "__context": {
      "plugin": "777c682f"
    },
    "sidebar": "814f3328",
    "items": [
      {
        "content": "7661071f"
      }
    ],
    "tag": "b2d4d9c2",
    "listMetadata": "556022be"
  },
  "/blog/tags/linkedin-5c1": {
    "__comp": "6875c492",
    "__context": {
      "plugin": "777c682f"
    },
    "sidebar": "814f3328",
    "items": [
      {
        "content": "7661071f"
      }
    ],
    "tag": "b18600ed",
    "listMetadata": "db5c031a"
  },
  "/markdown-page-02c": {
    "__comp": "1f391b9e",
    "__context": {
      "plugin": "b1f19375"
    },
    "content": "393be207"
  },
  "/docs-27f": {
    "__comp": "1be78505",
    "__context": {
      "plugin": "b21be71e"
    },
    "versionMetadata": "935f2afb"
  },
  "/docs/category/extras-88a": {
    "__comp": "14eb3368",
    "categoryGeneratedIndex": "91719550"
  },
  "/docs/category/tasks-70f": {
    "__comp": "14eb3368",
    "categoryGeneratedIndex": "389968de"
  },
  "/docs/Extras/proximamente-b0b": {
    "__comp": "17896441",
    "content": "042f6544"
  },
  "/docs/Extras/prueba1_IAW-18c": {
    "__comp": "17896441",
    "content": "06fea3ab"
  },
  "/docs/intro-99a": {
    "__comp": "17896441",
    "content": "f8409a7e"
  },
  "/docs/Tasks/apache_wsgi-83c": {
    "__comp": "17896441",
    "content": "bf46dd46"
  },
  "/docs/Tasks/apache2_fpm-b47": {
    "__comp": "17896441",
    "content": "f99e8129"
  },
  "/docs/Tasks/bookmedik-37d": {
    "__comp": "17896441",
    "content": "efa196ad"
  },
  "/docs/Tasks/cifrado_asimetrico-07c": {
    "__comp": "17896441",
    "content": "05b8823d"
  },
  "/docs/Tasks/cliente_vpn-817": {
    "__comp": "17896441",
    "content": "8efe011e"
  },
  "/docs/Tasks/clonacion_instantanea-211": {
    "__comp": "17896441",
    "content": "d94373a8"
  },
  "/docs/Tasks/compilacion_kernel-bc5": {
    "__comp": "17896441",
    "content": "eb4abe1b"
  },
  "/docs/Tasks/escenario_openstack-6ef": {
    "__comp": "17896441",
    "content": "9ebb1dcc"
  },
  "/docs/Tasks/gestion_paqueteria_aso-b86": {
    "__comp": "17896441",
    "content": "82f28520"
  },
  "/docs/Tasks/interconexion_bbdd-60e": {
    "__comp": "17896441",
    "content": "6183c210"
  },
  "/docs/Tasks/intro_git-221": {
    "__comp": "17896441",
    "content": "5d56c66f"
  },
  "/docs/Tasks/lemp-8ab": {
    "__comp": "17896441",
    "content": "19f6a984"
  },
  "/docs/Tasks/makefile_aso-e40": {
    "__comp": "17896441",
    "content": "e8d71a07"
  },
  "/docs/Tasks/manejo_modulos-bff": {
    "__comp": "17896441",
    "content": "1f5bd34a"
  },
  "/docs/Tasks/markdown-ebc": {
    "__comp": "17896441",
    "content": "596b171e"
  },
  "/docs/Tasks/markdown-features-4e3": {
    "__comp": "17896441",
    "content": "0de80381"
  },
  "/docs/Tasks/migracion_centos-7c2": {
    "__comp": "17896441",
    "content": "3b927334"
  },
  "/docs/Tasks/migracion_php-940": {
    "__comp": "17896441",
    "content": "a14eb6e2"
  },
  "/docs/Tasks/nginx_php-77d": {
    "__comp": "17896441",
    "content": "a168c652"
  },
  "/docs/Tasks/parametros_kernel-f29": {
    "__comp": "17896441",
    "content": "d41f5ee1"
  },
  "/docs/Tasks/peticion_http-71d": {
    "__comp": "17896441",
    "content": "379ad948"
  },
  "/docs/Tasks/ramas_uniones-260": {
    "__comp": "17896441",
    "content": "c9e876c3"
  },
  "/docs/Tasks/redes_openstack-b54": {
    "__comp": "17896441",
    "content": "f07f6973"
  },
  "/docs/Tasks/router_nat-bbb": {
    "__comp": "17896441",
    "content": "14682d54"
  },
  "/docs/Tasks/servidor_lamp-fb8": {
    "__comp": "17896441",
    "content": "0d16f3b7"
  },
  "/docs/Tasks/virtualhosting_apache-4ef": {
    "__comp": "17896441",
    "content": "b527b7e7"
  },
  "/docs/Tasks/virtualizacion_linux-3d7": {
    "__comp": "17896441",
    "content": "147aa350"
  },
  "/docs/Tasks/wordpress-b17": {
    "__comp": "17896441",
    "content": "9dde1a93"
  },
  "/-19f": {
    "__comp": "c4f5d8e4",
    "__context": {
      "plugin": "b1f19375"
    },
    "config": "5e9f5e1a"
  }
}